admin_watchdog/__init__.py
admin_watchdog/admin.py
admin_watchdog/handlers.py
admin_watchdog/models.py
admin_watchdog/locale/fr/LC_MESSAGES/django.mo
admin_watchdog/locale/fr/LC_MESSAGES/django.po
admin_watchdog/migrations/0001_initial.py
admin_watchdog/migrations/0002_auto_20141029_1058.py
admin_watchdog/migrations/__init__.py
admin_watchdog/static/admin_watchdog/admin.css
admin_watchdog/tests/__init__.py
admin_watchdog/tests/mocks.py
admin_watchdog/tests/settings.py
admin_watchdog/tests/tests.py
admin_watchdog/tests/urls.py
django_admin_watchdog-1.0.4.dist-info/LICENSE
django_admin_watchdog-1.0.4.dist-info/METADATA
django_admin_watchdog-1.0.4.dist-info/WHEEL
django_admin_watchdog-1.0.4.dist-info/top_level.txt
django_admin_watchdog-1.0.4.dist-info/RECORD
