Metadata-Version: 2.1
Name: django-admin-watchdog
Version: 1.0.4
Summary: A simple Django app to register logs in admin backoffice.
Home-page: https://github.com/makinacorpus/django-admin-watchdog
Author: Yann Fouillat
Author-email: yann.fouillat@makina-corpus.com
License: GPLv3+
Platform: UNKNOWN
Classifier: Environment :: Web Environment
Classifier: Framework :: Django
Classifier: Intended Audience :: Developers
Classifier: License :: OSI Approved :: GNU General Public License v3 or later (GPLv3+)
Classifier: Operating System :: OS Independent
Classifier: Programming Language :: Python
Classifier: Programming Language :: Python :: 2.7
Classifier: Topic :: Internet :: WWW/HTTP
Classifier: Topic :: Internet :: WWW/HTTP :: Dynamic Content
